<?xml version="1.0"?>
<?xml-stylesheet type="text/xsl" href="configuration.xsl"?>

<!-- Put site-specific property overrides in this file. -->

<configuration>
    <property>
        <name>io.compression.codecs</name>
        <value>org.apache.hadoop.io.compress.GzipCodec,org.apache.hadoop.io.compress.DefaultCodec,org.apache.hadoop.io.compress.BZip2Codec,com.hadoop.compression.lzo.LzoCodec,com.hadoop.compression.lzo.LzopCodec</value>
    </property>
    <property>
        <name>io.compression.codec.lzo.class</name>
        <value>com.hadoop.compression.lzo.LzoCodec</value>
    </property>
    <property>
        <name>fs.default.name</name>
        <value>hdfs://ec2-184-73-44-232.compute-1.amazonaws.com:9000</value>
    </property>
</configuration>
